passwordP/__init__.py
passwordP/passwordPP.py
passwordP-1.1.7.7.dist-info/LICENSE.txt
passwordP-1.1.7.7.dist-info/METADATA
passwordP-1.1.7.7.dist-info/WHEEL
passwordP-1.1.7.7.dist-info/top_level.txt
passwordP-1.1.7.7.dist-info/RECORD
