Metadata-Version: 2.1
Name: passwordP
Version: 1.1.7.7
Summary: password generator package
Author: Nipun dogra
Classifier: Programming Language :: Python :: 3
Classifier: License :: OSI Approved :: MIT License
Classifier: Operating System :: OS Independent
Requires-Python: >=3.6
License-File: LICENSE.txt
